shinalysis/__init__.py
shinalysis-0.1.1.dist-info/WHEEL
shinalysis-0.1.1.dist-info/entry_points.txt
shinalysis-0.1.1.dist-info/METADATA
shinalysis-0.1.1.dist-info/RECORD
